pip_earth/__init__.py
pip_package/__init__.py
pip_earth-0.2.dist-info/LICENSE.txt
pip_earth-0.2.dist-info/METADATA
pip_earth-0.2.dist-info/WHEEL
pip_earth-0.2.dist-info/top_level.txt
pip_earth-0.2.dist-info/RECORD
