Metadata-Version: 2.1
Name: pip_earth
Version: 0.2
Summary: Basic calculator
Author: vishnu
Author-email: gomatamvishnu@gmail.com
Classifier: Programming Language :: Python :: 3
Classifier: License :: OSI Approved :: MIT License
Classifier: Operating System :: OS Independent
License-File: LICENSE.txt
